{
  "attributes": {
    "application": {
      "ref": "application",
      "type": "ObjectId",
      "required": true
    },
    "routeNormalizedPath": {
      "type": "String"
    },
    "requestId": {
      "type": "String"
    },
    "request": {
      "sessionId": {
        "type": "String"
      },
      "ip": {
        "type": "String"
      },
      "path": {
        "type": "String"
      },
      "headers": {
        "type": "Object"
      },
      "method": {
        "type": "String"
      },
      "body": {
        "type": "Object"
      }
    },
    "response": {
      "status": {
        "type": "Number"
      },
      "body": {
        "type": "Object"
      },
      "headers": {
        "type": "Object"
      }
    }
  },
  "search": {
    "fields": [
      "requestId",
      "routeNormalizedPath"
    ]
  }
}
