{
  "paths": [
    {
      "method": "PATCH",
      "path": "/me",
      "requestBody": [
        {
          "name": "name",
          "description": "Full Name of user",
          "required": false,
          "schema": {
            "type": "string"
          }
        },
        {
          "name": "timeZone",
          "description": "Timezone in TZ Database standard (e.g. Europe/Amsterdam)",
          "required": false,
          "schema": {
            "type": "string"
          }
        }
      ],
      "responseBody": [
        {
          "name": "data",
          "description": "Updated user object",
          "schema": {
            "type": "User"
          }
        }
      ],
      "examples": []
    },
    {
      "method": "POST",
      "path": "/search",
      "requestBody": [
        {
          "name": "skip",
          "description": "Offset for paginating results",
          "required": false,
          "schema": {
            "default": 0,
            "type": "number"
          }
        },
        {
          "name": "sort",
          "description": "Sort object",
          "required": false,
          "schema": {
            "default": {
              "field": "createdAt",
              "order": "desc"
            },
            "type": "object",
            "properties": {
              "field": {
                "type": "string"
              },
              "order": {
                "type": "string"
              }
            },
            "additionalProperties": false,
            "patterns": [],
            "required": ["field", "order"]
          }
        },
        {
          "name": "limit",
          "description": "Maximum number of results to retrieve",
          "required": false,
          "schema": {
            "default": 50,
            "type": "number"
          }
        }
      ],
      "responseBody": [],
      "examples": []
    },
    {
      "method": "POST",
      "path": "/",
      "requestBody": [
        {
          "name": "email",
          "description": "E-mail address of user",
          "required": true,
          "schema": {
            "type": "string",
            "format": "email"
          }
        },
        {
          "name": "name",
          "description": "Full name of user",
          "required": true,
          "schema": {
            "type": "string"
          }
        },
        {
          "name": "roles",
          "description": "List of roles to assign to user",
          "required": false,
          "schema": {
            "type": "array",
            "items": {
              "type": "string"
            }
          }
        },
        {
          "name": "password",
          "description": "Password of at least 6 characters",
          "required": true,
          "schema": {
            "type": "string",
            "minLength": 6
          }
        }
      ],
      "responseBody": [
        {
          "name": "data",
          "description": "Created User object",
          "schema": {
            "type": "User"
          }
        }
      ],
      "examples": []
    },
    {
      "method": "DELETE",
      "path": "/:user",
      "responseBody": [],
      "examples": []
    },
    {
      "method": "PATCH",
      "path": "/:user",
      "requestBody": [
        {
          "name": "email",
          "description": "E-mail address of user",
          "required": false,
          "schema": {
            "type": "string"
          }
        },
        {
          "name": "name",
          "description": "Full name of user",
          "required": false,
          "schema": {
            "type": "string"
          }
        },
        {
          "name": "roles",
          "description": "List of roles for user",
          "required": false,
          "schema": {
            "type": "array",
            "items": {
              "type": "string"
            }
          }
        }
      ],
      "responseBody": [
        {
          "name": "data",
          "description": "Updated User object",
          "schema": {
            "type": "User"
          }
        }
      ],
      "examples": []
    },
    {
      "method": "GET",
      "path": "/me",
      "responseBody": [
        {
          "name": "data",
          "description": "Current User object",
          "schema": {
            "type": "User"
          }
        }
      ],
      "examples": []
    },
    {
      "method": "GET",
      "path": "/:user",
      "responseBody": [
        {
          "name": "data",
          "description": "User object matching request ID",
          "schema": {
            "type": "User"
          }
        }
      ],
      "examples": []
    }
  ],
  "objects": [
    {
      "name": "User",
      "attributes": [
        {
          "name": "name",
          "description": "Full Name of user",
          "schema": {
            "type": "string"
          }
        },
        {
          "name": "timeZone",
          "description": "Timezone in TZ Database standard (e.g. Europe/Amsterdam)",
          "schema": {
            "type": "string"
          }
        },
        {
          "name": "email",
          "description": "E-mail address of user",
          "required": true,
          "schema": {
            "type": "string",
            "format": "email"
          }
        },
        {
          "name": "roles",
          "description": "List of roles for user",
          "required": false,
          "schema": {
            "type": "array",
            "items": {
              "type": "string"
            }
          }
        }
      ]
    }
  ]
}
